ascnii/_version.py
ascnii/args.py
ascnii/ascnii.py
ascnii/utils.py
ascnii-0.0.1.dev21.dist-info/LICENSE
ascnii-0.0.1.dev21.dist-info/METADATA
ascnii-0.0.1.dev21.dist-info/WHEEL
ascnii-0.0.1.dev21.dist-info/entry_points.txt
ascnii-0.0.1.dev21.dist-info/top_level.txt
ascnii-0.0.1.dev21.dist-info/RECORD
