Metadata-Version: 2.1
Name: ascnii
Version: 0.0.1.dev21
Summary: View brain images in terminal using ASCII characters
Author: Leonard Sasse
Author-email: l.sasse@fz-juelich.de
Project-URL: repository, https://github.com/LeSasse/ascnii
Keywords: neuroimaging
Classifier: Development Status :: 4 - Beta
Classifier: Intended Audience :: Science/Research
Classifier: Intended Audience :: Developers
Classifier: License :: OSI Approved
Classifier: Natural Language :: English
Classifier: Topic :: Software Development
Classifier: Topic :: Scientific/Engineering
Classifier: Topic :: Scientific/Engineering :: Bio-Informatics
Classifier: Operating System :: OS Independent
Classifier: Programming Language :: Python :: 3
Requires-Python: >=3.7
License-File: LICENSE
Requires-Dist: nilearn <1.0,>=0.9.0
Requires-Dist: ascii-magic ==1.6
Requires-Dist: matplotlib >=3.6.3
Provides-Extra: dev
Requires-Dist: tox ; extra == 'dev'
